langchain_search/__init__.py
langchain_search/apps.py
langchain_search/util/__init__.py
langchain_search/util/django.py
langchain_search/util/langchain.py
langchain_search/util/mixins.py
langchain_search_django-0.7.0.dist-info/METADATA
langchain_search_django-0.7.0.dist-info/WHEEL
langchain_search_django-0.7.0.dist-info/top_level.txt
langchain_search_django-0.7.0.dist-info/RECORD
