Metadata-Version: 2.4
Name: langchain-search-django
Version: 0.7.0
Summary: A Django app for integrating LangChain with search capabilities
Requires-Python: >=3.11
Requires-Dist: django>=5.2.3
Requires-Dist: langchain==0.3.25
Requires-Dist: langchain-community==0.3.24
Requires-Dist: openai==1.85.0
Requires-Dist: langchain-openai==0.3.21
Requires-Dist: faker<26.0.0,>=25.0.0
Requires-Dist: pydantic==2.11.5
